ie_datasets/__init__.py
ie_datasets/datasets/__init__.py
ie_datasets/datasets/biored/README.md
ie_datasets/datasets/biored/__init__.py
ie_datasets/datasets/biored/__main__.py
ie_datasets/datasets/biored/load.py
ie_datasets/datasets/biored/summary.py
ie_datasets/datasets/biored/unit.py
ie_datasets/datasets/chemprot/README.md
ie_datasets/datasets/chemprot/__init__.py
ie_datasets/datasets/chemprot/__main__.py
ie_datasets/datasets/chemprot/load.py
ie_datasets/datasets/chemprot/summary.py
ie_datasets/datasets/chemprot/unit.py
ie_datasets/datasets/crossre/README.md
ie_datasets/datasets/crossre/__init__.py
ie_datasets/datasets/crossre/__main__.py
ie_datasets/datasets/crossre/load.py
ie_datasets/datasets/crossre/summary.py
ie_datasets/datasets/crossre/unit.py
ie_datasets/datasets/cuad/README.md
ie_datasets/datasets/cuad/__init__.py
ie_datasets/datasets/cuad/__main__.py
ie_datasets/datasets/cuad/load.py
ie_datasets/datasets/cuad/summary.py
ie_datasets/datasets/cuad/unit.py
ie_datasets/datasets/deft/README.md
ie_datasets/datasets/deft/__init__.py
ie_datasets/datasets/deft/__main__.py
ie_datasets/datasets/deft/load.py
ie_datasets/datasets/deft/summary.py
ie_datasets/datasets/deft/unit.py
ie_datasets/datasets/docred/README.md
ie_datasets/datasets/docred/__init__.py
ie_datasets/datasets/docred/__main__.py
ie_datasets/datasets/docred/load.py
ie_datasets/datasets/docred/schema.py
ie_datasets/datasets/docred/summary.py
ie_datasets/datasets/docred/unit.py
ie_datasets/datasets/hyperred/README.md
ie_datasets/datasets/hyperred/__init__.py
ie_datasets/datasets/hyperred/__main__.py
ie_datasets/datasets/hyperred/load.py
ie_datasets/datasets/hyperred/summary.py
ie_datasets/datasets/hyperred/unit.py
ie_datasets/datasets/knowledgenet/README.md
ie_datasets/datasets/knowledgenet/__init__.py
ie_datasets/datasets/knowledgenet/__main__.py
ie_datasets/datasets/knowledgenet/load.py
ie_datasets/datasets/knowledgenet/summary.py
ie_datasets/datasets/knowledgenet/unit.py
ie_datasets-0.0.8.dist-info/METADATA
ie_datasets-0.0.8.dist-info/WHEEL
ie_datasets-0.0.8.dist-info/licenses/LICENSE
ie_datasets-0.0.8.dist-info/RECORD
