Metadata-Version: 2.4
Name: ie-datasets
Version: 0.0.8
Summary: Load fully-typed information extraction data in a single line.
Project-URL: Homepage, https://github.com/adanomad/ie-datasets
Project-URL: Issues, https://github.com/adanomad/ie-datasets/issues
Author-email: Justin Xu <xu.justin.j@gmail.com>
License-Expression: MIT
License-File: LICENSE
Classifier: Operating System :: OS Independent
Classifier: Programming Language :: Python :: 3
Requires-Python: >=3.9
Requires-Dist: annotated-types>=0.7.0
Requires-Dist: datasets>=3.3.2
Requires-Dist: gdown>=5.2.0
Requires-Dist: pandas>=2.2.3
Requires-Dist: platformdirs>=4.3.6
Requires-Dist: pyarrow>=19.0.1
Requires-Dist: pybrat>=0.1.7
Requires-Dist: pydantic>=2.10.3
